tinysets/__init__.py
tinysets/utils.py
tinysets-0.0.3.dist-info/LICENSE
tinysets-0.0.3.dist-info/METADATA
tinysets-0.0.3.dist-info/WHEEL
tinysets-0.0.3.dist-info/top_level.txt
tinysets-0.0.3.dist-info/RECORD
