Metadata-Version: 2.1
Name: tinysets
Version: 0.0.3
Summary: Collection of different datasets
Home-page: https://github.com/yisaienkov/tinysets
Author: Yaroslav Isaienkov
Author-email: oiuygl@gmail.com
License: UNKNOWN
Platform: UNKNOWN
Classifier: Programming Language :: Python :: 3
Classifier: License :: OSI Approved :: MIT License
Classifier: Operating System :: OS Independent
Requires-Python: >=3.6
Provides-Extra: tests
Requires-Dist: pytest ; extra == 'tests'
